.coveragerc
LICENSE
MANIFEST.in
README.md
dev_requirements.txt
requirements.txt
setup.cfg
setup.py
versioneer.py
csirtg_dt/__init__.py
csirtg_dt/_version.py
csirtg_dt/constants.py
csirtg_dt/utils.py
csirtg_dt.egg-info/PKG-INFO
csirtg_dt.egg-info/SOURCES.txt
csirtg_dt.egg-info/dependency_links.txt
csirtg_dt.egg-info/entry_points.txt
csirtg_dt.egg-info/requires.txt
csirtg_dt.egg-info/top_level.txt
test/test_dt.py